kaena/__init__.py
kaena/ctape.cpython-39-x86_64-linux-gnu.so
kaena/tape.py
kaena-0.1.0.dist-info/METADATA
kaena-0.1.0.dist-info/WHEEL
kaena-0.1.0.dist-info/top_level.txt
kaena-0.1.0.dist-info/RECORD
