Metadata-Version: 2.1
Name: kaena
Version: 0.1.0
Summary: A modular Python library focused on efficiency and performance across various formats.
Author: Kaena
Author-email: kaena.core@gmail.com
License: Proprietary
Classifier: License :: Other/Proprietary License
Classifier: Programming Language :: Python :: 3
Classifier: Programming Language :: C
Classifier: Operating System :: OS Independent
